roseus/__init__.py
roseus/_version.py
roseus/generator.py
roseus/mpl.py
roseus/mpl.pyi
roseus/util.py
roseus/viscm_cam16ucs.py
roseus/cmap/__init__.py
roseus/cmap/arcus.npy
roseus/cmap/arcus.py
roseus/cmap/b.npy
roseus/cmap/b.py
roseus/cmap/cyanus.npy
roseus/cmap/cyanus.py
roseus/cmap/gr.npy
roseus/cmap/gr.py
roseus/cmap/lavendula.npy
roseus/cmap/lavendula.py
roseus/cmap/r.npy
roseus/cmap/r.py
roseus/cmap/rbg.npy
roseus/cmap/rbg.py
roseus/cmap/rg.npy
roseus/cmap/rg.py
roseus/cmap/roseus.npy
roseus/cmap/roseus.py
roseus/viscm/LICENSE-viscm.txt
roseus/viscm/colourmaptest.npy
roseus/viscm/st-helens_before-modified.npy
roseus-2.0.0.dist-info/METADATA
roseus-2.0.0.dist-info/WHEEL
roseus-2.0.0.dist-info/licenses/LICENSE.txt
roseus-2.0.0.dist-info/licenses/roseus/viscm/LICENSE-viscm.txt
roseus-2.0.0.dist-info/RECORD
