Metadata-Version: 2.3
Name: roseus
Version: 2.0.0
Summary: Colormap family with full range of lightness
Project-URL: Homepage, https://github.com/dofuuz/roseus
Project-URL: Source, https://github.com/dofuuz/roseus
Author: KEUM Myungchul
License-Expression: MIT
License-File: LICENSE.txt
License-File: roseus/viscm/LICENSE-viscm.txt
Keywords: visualization
Classifier: Development Status :: 4 - Beta
Classifier: Intended Audience :: Science/Research
Classifier: License :: OSI Approved :: MIT License
Classifier: Programming Language :: Python :: 3
Classifier: Topic :: Scientific/Engineering :: Visualization
Requires-Python: >=3.6
Provides-Extra: generate
Requires-Dist: colorspacious; extra == 'generate'
Requires-Dist: colour-science; extra == 'generate'
Requires-Dist: matplotlib; extra == 'generate'
Requires-Dist: numpy; extra == 'generate'
Requires-Dist: scipy; extra == 'generate'
